LeetcodeTijieItchargeFix1/README.md
LeetcodeTijieItchargeFix1/__init__.py
LeetcodeTijieItchargeFix1/__main__.py
LeetcodeTijieItchargeFix1/file.epub
LeetcodeTijieItchargeFix1/index.html
LeetcodeTijieItchargeFix1/css/__init__.py
LeetcodeTijieItchargeFix1/css/annotations.css
LeetcodeTijieItchargeFix1/css/main.css
LeetcodeTijieItchargeFix1/css/normalize.css
LeetcodeTijieItchargeFix1/css/popup.css
LeetcodeTijieItchargeFix1/font/__init__.py
LeetcodeTijieItchargeFix1/font/fontello.eot
LeetcodeTijieItchargeFix1/font/fontello.svg
LeetcodeTijieItchargeFix1/font/fontello.ttf
LeetcodeTijieItchargeFix1/font/fontello.woff
LeetcodeTijieItchargeFix1/img/__init__.py
LeetcodeTijieItchargeFix1/img/annotator-glyph-sprite.png
LeetcodeTijieItchargeFix1/img/annotator-icon-sprite.png
LeetcodeTijieItchargeFix1/img/apple-touch-icon.png
LeetcodeTijieItchargeFix1/img/cancelfullscreen.png
LeetcodeTijieItchargeFix1/img/close.png
LeetcodeTijieItchargeFix1/img/fullscreen.png
LeetcodeTijieItchargeFix1/img/loader.gif
LeetcodeTijieItchargeFix1/img/menu-icon.png
LeetcodeTijieItchargeFix1/img/save.png
LeetcodeTijieItchargeFix1/img/saved.png
LeetcodeTijieItchargeFix1/img/settings-s.png
LeetcodeTijieItchargeFix1/img/settings.png
LeetcodeTijieItchargeFix1/img/star.png
LeetcodeTijieItchargeFix1/js/__init__.py
LeetcodeTijieItchargeFix1/js/epub.js
LeetcodeTijieItchargeFix1/js/epub.min.js
LeetcodeTijieItchargeFix1/js/epub.min.map
LeetcodeTijieItchargeFix1/js/hooks.min.js
LeetcodeTijieItchargeFix1/js/hooks.min.map
LeetcodeTijieItchargeFix1/js/reader.js
LeetcodeTijieItchargeFix1/js/reader.js.map
LeetcodeTijieItchargeFix1/js/reader.min.js
LeetcodeTijieItchargeFix1/js/reader.min.map
LeetcodeTijieItchargeFix1/js/hooks/__init__.py
LeetcodeTijieItchargeFix1/js/hooks/extensions/__init__.py
LeetcodeTijieItchargeFix1/js/hooks/extensions/highlight.js
LeetcodeTijieItchargeFix1/js/libs/__init__.py
LeetcodeTijieItchargeFix1/js/libs/jquery.min.js
LeetcodeTijieItchargeFix1/js/libs/localforage.min.js
leetcode_tijie_itcharge_fix1-2025.3.25.1.dist-info/METADATA
leetcode_tijie_itcharge_fix1-2025.3.25.1.dist-info/WHEEL
leetcode_tijie_itcharge_fix1-2025.3.25.1.dist-info/entry_points.txt
leetcode_tijie_itcharge_fix1-2025.3.25.1.dist-info/top_level.txt
leetcode_tijie_itcharge_fix1-2025.3.25.1.dist-info/RECORD
